dsp/__init__.py
dsp/evaluation/__init__.py
dsp/evaluation/utils.py
dsp/modules/__init__.py
dsp/modules/azurecognitivesearch.py
dsp/modules/cache_utils.py
dsp/modules/cohere.py
dsp/modules/colbertv2.py
dsp/modules/gpt3.py
dsp/modules/hf.py
dsp/modules/hf_client.py
dsp/modules/hf_server.py
dsp/modules/lm.py
dsp/modules/sbert.py
dsp/modules/sentence_vectorizer.py
dsp/primitives/__init__.py
dsp/primitives/compiler.py
dsp/primitives/demonstrate.py
dsp/primitives/inspect.py
dsp/primitives/predict.py
dsp/primitives/primitives.py
dsp/primitives/search.py
dsp/templates/__init__.py
dsp/templates/template_v2.py
dsp/templates/template_v3.py
dsp/templates/utils.py
dsp/utils/__init__.py
dsp/utils/ann_utils.py
dsp/utils/dpr.py
dsp/utils/metrics.py
dsp/utils/settings.py
dsp/utils/utils.py
dspy_ml-0.1.9.dist-info/LICENSE
dspy_ml-0.1.9.dist-info/METADATA
dspy_ml-0.1.9.dist-info/WHEEL
dspy_ml-0.1.9.dist-info/top_level.txt
dspy_ml-0.1.9.dist-info/RECORD
