Metadata-Version: 2.1
Name: dspy-ml
Version: 0.1.9
Summary: Demonstrate-Search-Predict
Home-page: https://github.com/stanfordnlp/dsp
Author: Omar Khattab
Author-email: okhattab@stanford.edu
License: MIT License
Classifier: Development Status :: 3 - Alpha
Classifier: Intended Audience :: Science/Research
Classifier: License :: OSI Approved :: MIT License
Classifier: Operating System :: POSIX :: Linux
Classifier: Programming Language :: Python :: 3
Classifier: Programming Language :: Python :: 3.8
Classifier: Programming Language :: Python :: 3.9
Requires-Python: >=3.9
License-File: LICENSE
Requires-Dist: backoff
Requires-Dist: joblib
Requires-Dist: jupyter
Requires-Dist: openai
Requires-Dist: pandas
Requires-Dist: spacy
Requires-Dist: regex
Requires-Dist: ujson
Requires-Dist: tqdm
Requires-Dist: datasets
